pytalite/__init__.py
pytalite/interpretation.py
pytalite/plotwrapper.py
pytalite/util/__init__.py
pytalite/util/color.py
pytalite/util/data_ops.py
pytalite/util/plots.py
pytalite_spark/__init__.py
pytalite_spark/interpretation.py
pytalite_spark/plotwrapper.py
pytalite_spark/util/__init__.py
pytalite_spark/util/color.py
pytalite_spark/util/data_ops.py
pytalite_spark/util/plots.py
pytalite-1.0.0.dist-info/LICENSE
pytalite-1.0.0.dist-info/METADATA
pytalite-1.0.0.dist-info/WHEEL
pytalite-1.0.0.dist-info/top_level.txt
pytalite-1.0.0.dist-info/RECORD
