Metadata-Version: 2.1
Name: pytalite
Version: 1.0.0
Summary: Python/Pyspark Package for Model-agnostic Evaluation and Diagnosis.
Home-page: https://github.com/rallyhealth/pytalite/
Author: Jinghao Jia, Lun Yu
Author-email: jiajinghao1998@gmail.com, lun.yu@rallyhealth.com
License: MIT
Keywords: pytalite
Platform: UNKNOWN
License-File: LICENSE
Requires-Dist: matplotlib (>=1.4.3)
Requires-Dist: numpy (>=1.9)
Requires-Dist: scipy (>=0.15)
Requires-Dist: multiprocess (>=0.70.4)
